{
  "_description": "MACDX - MACD crossover strategy with 3-5 confirmations",
  "_version": "2.0.0",

  "preset": {
    "timeframe": "1h",
    "chart_period": "1D",
    "plotter_period": "1D",
    "loop_interval": 60,
    "position_check_interval": 15,
    "atr_sl_mult": 3.0,
    "atr_tp_mult": 3.0,
    "leverage": 6,
    "cooldown_after_close_hours": 0.5
  },

  "signal_rules": {
    "macd_cross_weight": 2,
    "rsi_zone_weight": 2,
    "ema_alignment_weight": 2,
    "not_sideways_weight": 1,
    "no_exhaustion_weight": 1,
    "volume_weight": 1,
    "min_score_for_signal": 4,
    "min_confirmations": 3,
    "min_volume_ratio": 0.5,
    "min_atr_ratio": 0.3,
    "rsi_long_max": 65,
    "rsi_long_min": 25,
    "rsi_short_max": 75,
    "rsi_short_min": 35,
    "bb_width_threshold": 0.5,
    "adx_threshold": 20,
    "consecutive_red_filter": true,
    "min_consecutive_for_block": 3,
    "enable_counter_trend_filter": true,
    "counter_trend_ema_threshold": 1.0,
    "enable_volume_filter": false,
    "volume_confirm_threshold": 0.8,
    "enable_risk_validation": false,
    "min_risk_reward_ratio": 1.2
  },

  "exit_rules": {
    "macd_weakening": {
      "enabled": true,
      "threshold": 0.5,
      "min_candles_after_peak": 3,
      "min_candles_in_trade": 2,
      "min_profit_pct": 0.5,
      "adx_override": 30
    },
    "trailing_profit": {
      "enabled": true,
      "activation_pnl": 2.0,
      "drawdown_levels": {
        "high_profit": { "threshold": 5.0, "max_drawdown": 0.3 },
        "medium_profit": { "threshold": 3.0, "max_drawdown": 0.4 },
        "low_profit": { "threshold": 2.0, "max_drawdown": 0.5 }
      }
    },
    "impulse_candle": {
      "enabled": true,
      "body_atr_multiplier": 2.0,
      "min_profit_pct": 1.5,
      "volume_confirm_ratio": 2.5,
      "volume_min_profit_pct": 1.0
    },
    "trailing_stop": {
      "enabled": true,
      "atr_multiplier": 1.5,
      "activation_atr": 1.0
    },
    "pump_guard": {
      "enabled": true,
      "reversal_pct": 0.5,
      "profit_lock_pct": 2.0,
      "max_staleness_sec": 60,
      "fallback_on_error": "skip"
    },
    "emergency": {
      "max_loss_atr": 2.0,
      "max_loss_pct": 1.1,
      "max_hold_candles": 16,
      "protect_matching_trend": true
    },
    "regime_adaptation": {
      "enabled": true,
      "TRENDING": {
        "weakening_threshold": 0.4,
        "trailing_drawdown": 0.5,
        "impulse_min_profit": 2.0
      },
      "RANGING": {
        "weakening_threshold": 0.6,
        "trailing_drawdown": 0.35,
        "impulse_min_profit": 0.8
      },
      "VOLATILE": {
        "weakening_threshold": 0.55,
        "trailing_drawdown": 0.3,
        "impulse_min_profit": 1.0
      },
      "TRANSITIONAL": {
        "weakening_threshold": 0.5,
        "trailing_drawdown": 0.4,
        "impulse_min_profit": 1.5
      }
    }
  }
}
